_uuid_cbr_c.cpython-38-x86_64-linux-gnu.so
uuid_cbr/__init__.py
uuid_cbr/__version__.py
uuid_cbr/uuid_cbr.py
uuid_cbr/uuid_cbr_c.py
uuid_cbr-1.0.0.dist-info/LICENSE
uuid_cbr-1.0.0.dist-info/METADATA
uuid_cbr-1.0.0.dist-info/WHEEL
uuid_cbr-1.0.0.dist-info/top_level.txt
uuid_cbr-1.0.0.dist-info/RECORD
