Metadata-Version: 2.1
Name: uuid-cbr
Version: 1.0.0
Summary: Python wrapper for the cbrf uuid library.
Home-page: https://github.com/Okeydj/cbr-uuid-python
Author: OkeyDJ <okeydj@gmail.com>
Author-email: okeydj@gmail.com
License: MIT
Platform: UNKNOWN
